{
"meta":{"test_sets":[],"test_metrics":[],"learn_metrics":[{"best_value":"Min","name":"Logloss"}],"launch_mode":"Train","parameters":"","iteration_count":100,"learn_sets":["learn"],"name":"experiment"},
"iterations":[
{"learn":[0.6868962235],"iteration":0,"passed_time":0.1513358481,"remaining_time":14.98224896},
{"learn":[0.6811668378],"iteration":1,"passed_time":0.1561872682,"remaining_time":7.653176142},
{"learn":[0.6761483022],"iteration":2,"passed_time":0.1604921799,"remaining_time":5.189247149},
{"learn":[0.6701915955],"iteration":3,"passed_time":0.1626247444,"remaining_time":3.902993866},
{"learn":[0.6648403949],"iteration":4,"passed_time":0.1646219813,"remaining_time":3.127817645},
{"learn":[0.6591976232],"iteration":5,"passed_time":0.1683400458,"remaining_time":2.637327385},
{"learn":[0.6535740474],"iteration":6,"passed_time":0.1730117305,"remaining_time":2.298584419},
{"learn":[0.6485128337],"iteration":7,"passed_time":0.1760630345,"remaining_time":2.024724896},
{"learn":[0.6438231426],"iteration":8,"passed_time":0.1807559064,"remaining_time":1.827643053},
{"learn":[0.6387024314],"iteration":9,"passed_time":0.1932792369,"remaining_time":1.739513132},
{"learn":[0.6337658506],"iteration":10,"passed_time":0.1969113827,"remaining_time":1.593192096},
{"learn":[0.6295186878],"iteration":11,"passed_time":0.1988820844,"remaining_time":1.458468619},
{"learn":[0.6250711339],"iteration":12,"passed_time":0.2014866014,"remaining_time":1.348410333},
{"learn":[0.6206584773],"iteration":13,"passed_time":0.2029089777,"remaining_time":1.246440863},
{"learn":[0.6155234157],"iteration":14,"passed_time":0.2044244738,"remaining_time":1.158405352},
{"learn":[0.6109656258],"iteration":15,"passed_time":0.2058072795,"remaining_time":1.080488217},
{"learn":[0.6065131332],"iteration":16,"passed_time":0.2069976976,"remaining_time":1.010635818},
{"learn":[0.6024658955],"iteration":17,"passed_time":0.2083746836,"remaining_time":0.9492624475},
{"learn":[0.5981163241],"iteration":18,"passed_time":0.2096400764,"remaining_time":0.893728747},
{"learn":[0.5944359963],"iteration":19,"passed_time":0.2109754727,"remaining_time":0.843901891},
{"learn":[0.5903473386],"iteration":20,"passed_time":0.2122713632,"remaining_time":0.7985446519},
{"learn":[0.5860272131],"iteration":21,"passed_time":0.2150680143,"remaining_time":0.762513869},
{"learn":[0.5819335701],"iteration":22,"passed_time":0.2173270873,"remaining_time":0.7275732922},
{"learn":[0.578231484],"iteration":23,"passed_time":0.2190979236,"remaining_time":0.6938100914},
{"learn":[0.5742347051],"iteration":24,"passed_time":0.2209514751,"remaining_time":0.6628544252},
{"learn":[0.5705737129],"iteration":25,"passed_time":0.2227917278,"remaining_time":0.6340995329},
{"learn":[0.5668879339],"iteration":26,"passed_time":0.2245522125,"remaining_time":0.6071226486},
{"learn":[0.5629385855],"iteration":27,"passed_time":0.2263127255,"remaining_time":0.5819470086},
{"learn":[0.5592214502],"iteration":28,"passed_time":0.2282809646,"remaining_time":0.5588947755},
{"learn":[0.555028427],"iteration":29,"passed_time":0.2335381198,"remaining_time":0.5449222796},
{"learn":[0.5513107793],"iteration":30,"passed_time":0.2372180401,"remaining_time":0.5280014441},
{"learn":[0.5475958338],"iteration":31,"passed_time":0.2414142645,"remaining_time":0.513005312},
{"learn":[0.5441152448],"iteration":32,"passed_time":0.2451171179,"remaining_time":0.4976620273},
{"learn":[0.5405760434],"iteration":33,"passed_time":0.2471846866,"remaining_time":0.4798290975},
{"learn":[0.5368840212],"iteration":34,"passed_time":0.2504802957,"remaining_time":0.465177692},
{"learn":[0.533618686],"iteration":35,"passed_time":0.2534982885,"remaining_time":0.4506636241},
{"learn":[0.5300640161],"iteration":36,"passed_time":0.2559283401,"remaining_time":0.4357698764},
{"learn":[0.526883012],"iteration":37,"passed_time":0.2585389351,"remaining_time":0.4218266836},
{"learn":[0.5238433672],"iteration":38,"passed_time":0.2610103479,"remaining_time":0.4082469544},
{"learn":[0.5210698543],"iteration":39,"passed_time":0.2632103714,"remaining_time":0.3948155571},
{"learn":[0.5178157012],"iteration":40,"passed_time":0.2657396668,"remaining_time":0.382405862},
{"learn":[0.5147727018],"iteration":41,"passed_time":0.2680411163,"remaining_time":0.3701520177},
{"learn":[0.5121234025],"iteration":42,"passed_time":0.2704541252,"remaining_time":0.3585089566},
{"learn":[0.5089591248],"iteration":43,"passed_time":0.272514436,"remaining_time":0.3468365549},
{"learn":[0.5057604624],"iteration":44,"passed_time":0.2742420646,"remaining_time":0.3351847456},
{"learn":[0.5027618183],"iteration":45,"passed_time":0.2761717224,"remaining_time":0.3242015872},
{"learn":[0.5004360521],"iteration":46,"passed_time":0.2787950494,"remaining_time":0.3143859067},
{"learn":[0.497155062],"iteration":47,"passed_time":0.2798992625,"remaining_time":0.3032242011},
{"learn":[0.4944431901],"iteration":48,"passed_time":0.2809940571,"remaining_time":0.2924632023},
{"learn":[0.4919120009],"iteration":49,"passed_time":0.28214477,"remaining_time":0.28214477},
{"learn":[0.48917045],"iteration":50,"passed_time":0.2837625835,"remaining_time":0.272634639},
{"learn":[0.4868202231],"iteration":51,"passed_time":0.2853811103,"remaining_time":0.2634287172},
{"learn":[0.4837957206],"iteration":52,"passed_time":0.2871951719,"remaining_time":0.254682511},
{"learn":[0.4811921278],"iteration":53,"passed_time":0.2888140221,"remaining_time":0.2460267596},
{"learn":[0.4783520354],"iteration":54,"passed_time":0.2910058214,"remaining_time":0.2380956721},
{"learn":[0.4758856087],"iteration":55,"passed_time":0.2937991102,"remaining_time":0.230842158},
{"learn":[0.4735583981],"iteration":56,"passed_time":0.2959483898,"remaining_time":0.2232593116},
{"learn":[0.4713655115],"iteration":57,"passed_time":0.2976914297,"remaining_time":0.215569656},
{"learn":[0.469407587],"iteration":58,"passed_time":0.2997735914,"remaining_time":0.2083172415},
{"learn":[0.4668758853],"iteration":59,"passed_time":0.3019761314,"remaining_time":0.201317421},
{"learn":[0.4643419938],"iteration":60,"passed_time":0.307009795,"remaining_time":0.1962849509},
{"learn":[0.4618685317],"iteration":61,"passed_time":0.3091644232,"remaining_time":0.1894878723},
{"learn":[0.4593694442],"iteration":62,"passed_time":0.3116710338,"remaining_time":0.1830448929},
{"learn":[0.4569377284],"iteration":63,"passed_time":0.3152798845,"remaining_time":0.177344935},
{"learn":[0.4547076616],"iteration":64,"passed_time":0.3178513792,"remaining_time":0.1711507427},
{"learn":[0.4524405543],"iteration":65,"passed_time":0.319424515,"remaining_time":0.1645520229},
{"learn":[0.4500223966],"iteration":66,"passed_time":0.3211578703,"remaining_time":0.1581822346},
{"learn":[0.4477407528],"iteration":67,"passed_time":0.3230415141,"remaining_time":0.152019536},
{"learn":[0.4455854191],"iteration":68,"passed_time":0.3250489747,"remaining_time":0.1460364959},
{"learn":[0.4433541409],"iteration":69,"passed_time":0.3285865437,"remaining_time":0.1408228044},
{"learn":[0.4421849679],"iteration":70,"passed_time":0.3318273857,"remaining_time":0.1355351294},
{"learn":[0.4401243552],"iteration":71,"passed_time":0.3328832622,"remaining_time":0.129454602},
{"learn":[0.4382626892],"iteration":72,"passed_time":0.3374551216,"remaining_time":0.1248121683},
{"learn":[0.4363443677],"iteration":73,"passed_time":0.3403676698,"remaining_time":0.1195886407},
{"learn":[0.4349537442],"iteration":74,"passed_time":0.3433671867,"remaining_time":0.1144557289},
{"learn":[0.4326437725],"iteration":75,"passed_time":0.3459001649,"remaining_time":0.109231631},
{"learn":[0.4307933352],"iteration":76,"passed_time":0.3488816334,"remaining_time":0.104211397},
{"learn":[0.4287280167],"iteration":77,"passed_time":0.3506411541,"remaining_time":0.09889878706},
{"learn":[0.4269560399],"iteration":78,"passed_time":0.3534873983,"remaining_time":0.09396500462},
{"learn":[0.4250751315],"iteration":79,"passed_time":0.3585239099,"remaining_time":0.08963097747},
{"learn":[0.4230455955],"iteration":80,"passed_time":0.3611741688,"remaining_time":0.08471986676},
{"learn":[0.4213620497],"iteration":81,"passed_time":0.3627295498,"remaining_time":0.0796235597},
{"learn":[0.4195833637],"iteration":82,"passed_time":0.3645424507,"remaining_time":0.07466532122},
{"learn":[0.418023286],"iteration":83,"passed_time":0.3665460365,"remaining_time":0.06981829267},
{"learn":[0.4167958733],"iteration":84,"passed_time":0.3690714656,"remaining_time":0.06513025863},
{"learn":[0.4150030699],"iteration":85,"passed_time":0.371305538,"remaining_time":0.06044508758},
{"learn":[0.4131806342],"iteration":86,"passed_time":0.3735505491,"remaining_time":0.05581789814},
{"learn":[0.4116836417],"iteration":87,"passed_time":0.3747243015,"remaining_time":0.05109876839},
{"learn":[0.4099462359],"iteration":88,"passed_time":0.37590192,"remaining_time":0.04645978786},
{"learn":[0.4083855992],"iteration":89,"passed_time":0.3773059324,"remaining_time":0.04192288138},
{"learn":[0.4067532111],"iteration":90,"passed_time":0.3804751938,"remaining_time":0.03762941478},
{"learn":[0.4050045301],"iteration":91,"passed_time":0.382733679,"remaining_time":0.03328118948},
{"learn":[0.4035695047],"iteration":92,"passed_time":0.3847887897,"remaining_time":0.02896259707},
{"learn":[0.4018771065],"iteration":93,"passed_time":0.387195592,"remaining_time":0.02471461226},
{"learn":[0.4004807056],"iteration":94,"passed_time":0.3885357881,"remaining_time":0.02044925201},
{"learn":[0.3989565501],"iteration":95,"passed_time":0.3910273894,"remaining_time":0.01629280789},
{"learn":[0.3971370963],"iteration":96,"passed_time":0.393933564,"remaining_time":0.01218351229},
{"learn":[0.3953708502],"iteration":97,"passed_time":0.3959475325,"remaining_time":0.008080561887},
{"learn":[0.3937352007],"iteration":98,"passed_time":0.3986245711,"remaining_time":0.004026510819},
{"learn":[0.3921140879],"iteration":99,"passed_time":0.4013500875,"remaining_time":0}
]}